{"d":[{"i":"t55t","n":"Charmander","b":1,"s":"dua","t":643,"x":["Obsidian Flames Elite Trainer Box"],"e":"044"}],"n":"Obsidian Flames Elite Trainer Box","t":1,"f":{"1":{"pf":null},"2":{"pf":null},"3":{"pf":null},"4":{"gi":{"t55t":1},"g":1,"pf":null},"5":{"hi":{"t55t":3},"h":3,"pf":null},"6":{"gi":{"t55t":1},"hi":{"t55t":3},"g":1,"h":3,"pf":null},"7":{"gi":{"t55t":3},"hi":{"t55t":7},"g":3,"h":7,"pf":null},"8":{"gi":{"t55t":36},"hi":{"t55t":81},"g":36,"h":81,"pf":null},"9":{"gi":{"t55t":198},"hi":{"t55t":157},"g":198,"h":157,"pf":null},"10":{"gi":{"t55t":149},"pfI":{"t55t":4},"g":149,"h":null,"pf":4},"t":{"g":388,"h":251,"pf":4}},"j":[{"k":"1700165571644","f":{"4":{"gi":{"t55t":-1},"g":-1},"5":{"hi":{"t55t":-3},"h":-3},"6":{"gi":{"t55t":-1},"hi":{"t55t":-3},"g":-1,"h":-3},"7":{"gi":{"t55t":-3},"hi":{"t55t":-7},"g":-3,"h":-7},"8":{"gi":{"t55t":-36},"hi":{"t55t":-81},"g":-36,"h":-81},"9":{"gi":{"t55t":-198},"hi":{"t55t":-157},"g":-198,"h":-157},"10":{"gi":{"t55t":-149},"pfI":{"t55t":-4},"g":-149,"pf":-4},"t":{"gi":{"t55t":-388},"hi":{"t55t":-251},"pfI":{"t55t":-4},"g":-388,"h":-251,"pf":-4}}}]}